photo_objects/__init__.py
photo_objects/config.py
photo_objects/error.py
photo_objects/img.py
photo_objects/utils.py
photo_objects/django/__init__.py
photo_objects/django/admin.py
photo_objects/django/apps.py
photo_objects/django/conf.py
photo_objects/django/context_processors.py
photo_objects/django/forms.py
photo_objects/django/models.py
photo_objects/django/objsto.py
photo_objects/django/signals.py
photo_objects/django/urls.py
photo_objects/django/api/__init__.py
photo_objects/django/api/album.py
photo_objects/django/api/auth.py
photo_objects/django/api/backup.py
photo_objects/django/api/photo.py
photo_objects/django/api/photo_change_request.py
photo_objects/django/api/utils.py
photo_objects/django/management/__init__.py
photo_objects/django/management/commands/__init__.py
photo_objects/django/management/commands/clean-scaled-photos.py
photo_objects/django/management/commands/create-initial-admin-account.py
photo_objects/django/management/commands/restore-backup.py
photo_objects/django/migrations/0001_initial.py
photo_objects/django/migrations/0002_created_at_updated_at.py
photo_objects/django/migrations/0003_admin_visibility.py
photo_objects/django/migrations/0004_camera_setup_and_settings.py
photo_objects/django/migrations/0005_sitesettings.py
photo_objects/django/migrations/0006_photo_alt_text.py
photo_objects/django/migrations/0007_backup.py
photo_objects/django/migrations/0008_sitesettings_copyright_notice.py
photo_objects/django/migrations/__init__.py
photo_objects/django/templatetags/__init__.py
photo_objects/django/templatetags/photo_objects_extras.py
photo_objects/django/tests/__init__.py
photo_objects/django/tests/test_album.py
photo_objects/django/tests/test_auth.py
photo_objects/django/tests/test_commands.py
photo_objects/django/tests/test_img.py
photo_objects/django/tests/test_og_meta.py
photo_objects/django/tests/test_photo.py
photo_objects/django/tests/test_photo_change_requests.py
photo_objects/django/tests/test_utils.py
photo_objects-0.10.4.dist-info/licenses/LICENSE
photo_objects-0.10.4.dist-info/METADATA
photo_objects-0.10.4.dist-info/WHEEL
photo_objects-0.10.4.dist-info/top_level.txt
photo_objects-0.10.4.dist-info/RECORD
