Metadata-Version: 2.4
Name: photo-objects
Version: 0.10.4
Summary: Application for storing photos in S3 compatible object-storage.
Author: Toni Kangas
License: MIT License
Project-URL: Homepage, https://github.com/kangasta/photo-objects
Project-URL: Repository, https://github.com/kangasta/photo-objects.git
Classifier: Environment :: Web Environment
Classifier: Framework :: Django
Classifier: Framework :: Django :: 6.0
Classifier: Intended Audience :: Developers
Classifier: License :: OSI Approved :: MIT License
Classifier: Operating System :: OS Independent
Classifier: Programming Language :: Python
Classifier: Programming Language :: Python :: 3
Classifier: Programming Language :: Python :: 3 :: Only
Classifier: Topic :: Internet :: WWW/HTTP
Classifier: Topic :: Internet :: WWW/HTTP :: Dynamic Content
Requires-Python: >=3.10
License-File: LICENSE
Requires-Dist: markdown~=3.7
Requires-Dist: minio<7.2.19,>=7.2.0
Requires-Dist: pillow~=12.0
Dynamic: license-file
